plottie
