Metadata-Version: 1.1
Name: plottie
Version: 0.3.3
Summary: Command-line software for plotting and cutting using Silhouette devices.
Home-page: https://github.com/mossblaser/plottie
Author: Jonathan Heathcote
Author-email: UNKNOWN
License: LGPLv3
Keywords: svg plotter cutter silhouette
Platform: UNKNOWN
Classifier: Development Status :: 3 - Alpha
Classifier: Intended Audience :: Developers
Classifier: License :: OSI Approved :: GNU Lesser General Public License v3 (LGPLv3)
Classifier: Operating System :: POSIX :: Linux
Classifier: Operating System :: Microsoft :: Windows
Classifier: Operating System :: MacOS
Classifier: Programming Language :: Python :: 3
Classifier: Programming Language :: Python :: 3.5
